{"nodes": [{"id": "sections_articles_articles", "label": "Articles Section", "file_type": "code", "source_file": "components/sections/articles.tsx", "source_location": "line 45", "source_url": null, "captured_at": null, "author": null, "contributor": null}, {"id": "sections_articles_articlecard", "label": "ArticleCard (internal)", "file_type": "code", "source_file": "components/sections/articles.tsx", "source_location": "line 11", "source_url": null, "captured_at": null, "author": null, "contributor": null}], "edges": [{"source": "sections_articles_articles", "target": "lib_hooks_usesectioninview", "relation": "references", "confidence": "EXTRACTED", "confidence_score": 1.0, "source_file": "components/sections/articles.tsx", "source_location": "line 5", "weight": 1.0}, {"source": "sections_articles_articles", "target": "content_portfolio", "relation": "references", "confidence": "EXTRACTED", "confidence_score": 1.0, "source_file": "components/sections/articles.tsx", "source_location": "line 6", "weight": 1.0}, {"source": "sections_articles_articles", "target": "ui_sectionheader_sectionheader", "relation": "references", "confidence": "EXTRACTED", "confidence_score": 1.0, "source_file": "components/sections/articles.tsx", "source_location": "line 8", "weight": 1.0}, {"source": "sections_articles_articles", "target": "ui_reveal_reveal", "relation": "references", "confidence": "EXTRACTED", "confidence_score": 1.0, "source_file": "components/sections/articles.tsx", "source_location": "line 9", "weight": 1.0}, {"source": "sections_articles_articles", "target": "types_portfolio", "relation": "references", "confidence": "EXTRACTED", "confidence_score": 1.0, "source_file": "components/sections/articles.tsx", "source_location": "line 7", "weight": 1.0}, {"source": "sections_articles_articles", "target": "sections_articles_articlecard", "relation": "calls", "confidence": "EXTRACTED", "confidence_score": 1.0, "source_file": "components/sections/articles.tsx", "source_location": "line 66", "weight": 1.0}, {"source": "sections_articles_articles", "target": "concept_section_tracking", "relation": "references", "confidence": "INFERRED", "confidence_score": 0.85, "source_file": "components/sections/articles.tsx", "source_location": null, "weight": 0.85}], "hyperedges": []}